disco_microbe/__init__.py
disco_microbe/_version.py
disco_microbe/disco_microbe.py
disco_microbe-1.0.0.dist-info/LICENSE.md
disco_microbe-1.0.0.dist-info/METADATA
disco_microbe-1.0.0.dist-info/WHEEL
disco_microbe-1.0.0.dist-info/entry_points.txt
disco_microbe-1.0.0.dist-info/top_level.txt
disco_microbe-1.0.0.dist-info/RECORD
